LICENSE
README.md
pyproject.toml
setup.py
pypayz/__init__.py
pypayz/payout.py
pypayz/schemas.py
pypayz/webhook.py
pypayz/widget.py
pypayz.egg-info/PKG-INFO
pypayz.egg-info/SOURCES.txt
pypayz.egg-info/dependency_links.txt
pypayz.egg-info/top_level.txt
pypayz/abstract/__init__.py
pypayz/abstract/wallex_client.py
pypayz/host2host/__init__.py
pypayz/host2host/exchange.py
pypayz/host2host/payout.py
pypayz/utils/__init__.py
pypayz/utils/calculus.py