Metadata-Version: 2.1
Name: pypayz
Version: 0.1.10
Summary: pypaiz
Author: PyDev
Author-email: pydev1510@yandex.ru
Classifier: Programming Language :: Python :: 3.10
Classifier: License :: OSI Approved :: MIT License
Classifier: Operating System :: OS Independent
Requires-Python: >=3.10
License-File: LICENSE
